jebasa/__init__.py
jebasa/alignment.py
jebasa/audio.py
jebasa/cli.py
jebasa/config.py
jebasa/dictionary.py
jebasa/exceptions.py
jebasa/pipeline.py
jebasa/subtitles.py
jebasa/text.py
jebasa/utils.py
jebasa-0.1.2.dist-info/METADATA
jebasa-0.1.2.dist-info/WHEEL
jebasa-0.1.2.dist-info/entry_points.txt
jebasa-0.1.2.dist-info/licenses/LICENSE
jebasa-0.1.2.dist-info/RECORD
