Metadata-Version: 2.4
Name: jebasa
Version: 0.1.2
Summary: Japanese ebook audio subtitle aligner - Create synchronized subtitles from Japanese audiobooks and EPUB files
Project-URL: Homepage, https://github.com/OCboy5/jebasa
Project-URL: Documentation, https://jebasa.readthedocs.io
Project-URL: Repository, https://github.com/OCboy5/jebasa
Project-URL: Bug Tracker, https://github.com/OCboy5/jebasa/issues
Author-email: OCboy5 <your.email@example.com>
License-Expression: MIT
License-File: LICENSE
Keywords: alignment,audio,epub,japanese,mfa,nlp,subtitles
Classifier: Development Status :: 4 - Beta
Classifier: Intended Audience :: Developers
Classifier: Intended Audience :: Education
Classifier: Intended Audience :: Science/Research
Classifier: License :: OSI Approved :: MIT License
Classifier: Operating System :: OS Independent
Classifier: Programming Language :: Python :: 3
Classifier: Programming Language :: Python :: 3.8
Classifier: Programming Language :: Python :: 3.9
Classifier: Programming Language :: Python :: 3.10
Classifier: Programming Language :: Python :: 3.11
Classifier: Programming Language :: Python :: 3.12
Classifier: Topic :: Multimedia :: Sound/Audio :: Analysis
Classifier: Topic :: Scientific/Engineering :: Information Analysis
Classifier: Topic :: Text Processing :: Linguistic
Requires-Python: >=3.8
Requires-Dist: beautifulsoup4>=4.9.0
Requires-Dist: click>=8.0.0
Requires-Dist: fugashi>=1.2.0
Requires-Dist: lxml>=4.6.0
Requires-Dist: pathlib-mate>=1.0.0
Requires-Dist: pydantic>=2.0.0
Requires-Dist: pydub>=0.25.0
Requires-Dist: rich>=10.0.0
Requires-Dist: textgrid>=1.5
Requires-Dist: tqdm>=4.60.0
Requires-Dist: unidic-lite
Provides-Extra: dev
Requires-Dist: black>=22.0.0; extra == 'dev'
Requires-Dist: flake8>=5.0.0; extra == 'dev'
Requires-Dist: isort>=5.10.0; extra == 'dev'
Requires-Dist: mypy>=1.0.0; extra == 'dev'
Requires-Dist: pre-commit>=2.20.0; extra == 'dev'
Requires-Dist: pytest-cov>=4.0.0; extra == 'dev'
Requires-Dist: pytest>=7.0.0; extra == 'dev'
Provides-Extra: docs
Requires-Dist: mkdocs-material>=8.0.0; extra == 'docs'
Requires-Dist: mkdocs>=1.4.0; extra == 'docs'
Requires-Dist: mkdocstrings[python]>=0.18.0; extra == 'docs'
